TMtest1/__init__.py
TMtest1/setup.py
TMtest1/test_function.py
TMtest1/configs/__init__.py
TMtest1/configs/_base_/__init__.py
TMtest1/test/__init__.py
TMtest1/tools/__init__.py
TMtest1/trademaster/__init__.py
TMtest1/trademaster/agents/__init__.py
TMtest1/trademaster/agents/builder.py
TMtest1/trademaster/agents/custom.py
TMtest1/trademaster/agents/algorithmic_trading/__init__.py
TMtest1/trademaster/agents/algorithmic_trading/dqn.py
TMtest1/trademaster/agents/high_frequency_trading/__init__.py
TMtest1/trademaster/agents/high_frequency_trading/ddqn.py
TMtest1/trademaster/agents/order_execution/__init__.py
TMtest1/trademaster/agents/order_execution/eteo.py
TMtest1/trademaster/agents/order_execution/pd.py
TMtest1/trademaster/agents/portfolio_management/__init__.py
TMtest1/trademaster/agents/portfolio_management/deeptrader.py
TMtest1/trademaster/agents/portfolio_management/eiie.py
TMtest1/trademaster/agents/portfolio_management/investor_imitator.py
TMtest1/trademaster/collector/__init__.py
TMtest1/trademaster/collector/binance.py
TMtest1/trademaster/collector/builder.py
TMtest1/trademaster/collector/custom.py
TMtest1/trademaster/collector/helper/__init__.py
TMtest1/trademaster/collector/helper/celery_app.py
TMtest1/trademaster/collector/helper/celery_config.py
TMtest1/trademaster/collector/helper/pika_connection.py
TMtest1/trademaster/collector/helper/run_celery.py
TMtest1/trademaster/collector/helper/websocket_consumer.py
TMtest1/trademaster/collector/helper/websocket_producer.py
TMtest1/trademaster/datasets/__init__.py
TMtest1/trademaster/datasets/builder.py
TMtest1/trademaster/datasets/custom.py
TMtest1/trademaster/datasets/algorithmic_trading/__init__.py
TMtest1/trademaster/datasets/algorithmic_trading/dataset.py
TMtest1/trademaster/datasets/high_frequency_trading/__init__.py
TMtest1/trademaster/datasets/high_frequency_trading/dataset.py
TMtest1/trademaster/datasets/order_execution/__init__.py
TMtest1/trademaster/datasets/order_execution/dataset.py
TMtest1-0.0.9.dist-info/METADATA
TMtest1-0.0.9.dist-info/WHEEL
TMtest1-0.0.9.dist-info/top_level.txt
TMtest1-0.0.9.dist-info/RECORD
